perceptron/Perceptron.py
perceptron/__init__.py
My_package_VeluruBhanuprakash-0.0.1.dist-info/LICENSE
My_package_VeluruBhanuprakash-0.0.1.dist-info/METADATA
My_package_VeluruBhanuprakash-0.0.1.dist-info/WHEEL
My_package_VeluruBhanuprakash-0.0.1.dist-info/top_level.txt
My_package_VeluruBhanuprakash-0.0.1.dist-info/RECORD
