Metadata-Version: 2.1
Name: My-package-VeluruBhanuprakash
Version: 0.0.1
Summary: A small package of perceptron
Home-page: https://github.com/VeluruBhanuprakash/My_package
Author: VeluruBhanuprakash
Author-email: bhanuprakash@gmail.com
License: UNKNOWN
Project-URL: Bug Tracker, https://github.com/VeluruBhanuprakash/My_package/issues
Platform: UNKNOWN
Classifier: Programming Language :: Python :: 3
Classifier: License :: OSI Approved :: MIT License
Classifier: Operating System :: OS Independent
Requires-Python: >=3.6
License-File: LICENSE
Requires-Dist: numpy
Requires-Dist: joblib
Requires-Dist: pandas
